LICENSE.md
README.md
pyproject.toml
src/spectrocrunch/__init__.py
src/spectrocrunch.egg-info/PKG-INFO
src/spectrocrunch.egg-info/SOURCES.txt
src/spectrocrunch.egg-info/dependency_links.txt
src/spectrocrunch.egg-info/requires.txt
src/spectrocrunch.egg-info/top_level.txt
src/spectrocrunch/align/__init__.py
src/spectrocrunch/align/align.py
src/spectrocrunch/align/alignDest.py
src/spectrocrunch/align/alignElastix.py
src/spectrocrunch/align/alignFFT.py
src/spectrocrunch/align/alignSift.py
src/spectrocrunch/align/alignSimple.py
src/spectrocrunch/align/alignSource.py
src/spectrocrunch/align/transform.py
src/spectrocrunch/align/types.py
src/spectrocrunch/align/tests/__init__.py
src/spectrocrunch/align/tests/helper_teststack.py
src/spectrocrunch/align/tests/test_align.py
src/spectrocrunch/align/tests/test_alignSourceDest.py
src/spectrocrunch/align/tests/test_teststack.py
src/spectrocrunch/align/tests/test_transform.py
src/spectrocrunch/detectors/__init__.py
src/spectrocrunch/detectors/area.py
src/spectrocrunch/detectors/base.py
src/spectrocrunch/detectors/diode.py
src/spectrocrunch/detectors/xrf.py
src/spectrocrunch/detectors/tests/__init__.py
src/spectrocrunch/detectors/tests/test_area.py
src/spectrocrunch/detectors/tests/test_base.py
src/spectrocrunch/detectors/tests/test_diode.py
src/spectrocrunch/detectors/tests/test_xrf.py
src/spectrocrunch/fullfield/__init__.py
src/spectrocrunch/fullfield/estimate_id21.py
src/spectrocrunch/fullfield/import_id21.py
src/spectrocrunch/fullfield/tests/__init__.py
src/spectrocrunch/geometries/__init__.py
src/spectrocrunch/geometries/base.py
src/spectrocrunch/geometries/diode.py
src/spectrocrunch/geometries/flatarea.py
src/spectrocrunch/geometries/qxrf.py
src/spectrocrunch/geometries/xrf.py
src/spectrocrunch/geometries/tests/__init__.py
src/spectrocrunch/geometries/tests/test_base.py
src/spectrocrunch/geometries/tests/test_diode.py
src/spectrocrunch/geometries/tests/test_flatarea.py
src/spectrocrunch/geometries/tests/test_qxrf.py
src/spectrocrunch/geometries/tests/test_xrf.py
src/spectrocrunch/instruments/__init__.py
src/spectrocrunch/instruments/configuration.py
src/spectrocrunch/instruments/tests/__init__.py
