Metadata-Version: 2.2
Name: spectrocrunch
Version: 1.0.0
Summary: Spectroscopic imaging library (XRF/XAS)
Author-email: ESRF <dau-pydev@esrf.fr>
License: # MIT License
Project-URL: Homepage, https://github.com/woutdenolf/spectrocrunch
Classifier: Intended Audience :: Science/Research
Classifier: License :: OSI Approved :: MIT License
Classifier: Programming Language :: Python :: 3
Requires-Python: >=3.8
License-File: LICENSE.md
Requires-Dist: setuptools
Requires-Dist: numpy
Requires-Dist: future
Requires-Dist: scipy
Requires-Dist: h5py
Requires-Dist: fabio
Requires-Dist: silx
Requires-Dist: pyparsing
Requires-Dist: shapely
Requires-Dist: matplotlib
Requires-Dist: uncertainties
Requires-Dist: pint
Requires-Dist: pandas
Requires-Dist: scikit-image
Requires-Dist: xlsxwriter
Requires-Dist: xlrd
Requires-Dist: openpyxl
Requires-Dist: python-dateutil
Requires-Dist: jsonpickle
Requires-Dist: testfixtures
Requires-Dist: future
Requires-Dist: cvxopt
Requires-Dist: pymca5
Provides-Extra: physics
Requires-Dist: xraylib; extra == "physics"
Requires-Dist: cctbx; extra == "physics"
Requires-Dist: fdmnes; extra == "physics"
Requires-Dist: PyTMM; extra == "physics"
Provides-Extra: elastix
Requires-Dist: SimpleITK; extra == "elastix"
Provides-Extra: test
Requires-Dist: pytest; extra == "test"
Requires-Dist: testfixtures; extra == "test"
Provides-Extra: dev
Requires-Dist: spectrocrunch[test]; extra == "dev"
Requires-Dist: black[jupyter]>=25; extra == "dev"
Requires-Dist: flake8>=4; extra == "dev"
Requires-Dist: flake8_nb>=0.3.1; extra == "dev"
Provides-Extra: doc
Requires-Dist: spectrocrunch[test]; extra == "doc"
Requires-Dist: sphinx; extra == "doc"
Requires-Dist: nbsphinx; extra == "doc"
Requires-Dist: sphinx-autodoc-typehints; extra == "doc"
Requires-Dist: pydata-sphinx-theme; extra == "doc"
